setup.py
walletkit/__init__.py
walletkit/walletkit.py
walletkit.egg-info/PKG-INFO
walletkit.egg-info/SOURCES.txt
walletkit.egg-info/dependency_links.txt
walletkit.egg-info/requires.txt
walletkit.egg-info/top_level.txt