Metadata-Version: 1.0
Name: walletkit
Version: 1.0.1
Summary: Walletkit Python SDK
Home-page: http://walletkit.com/docs/sdk/python
Author: Walletkit
Author-email: support@walletkit.com
License: UNKNOWN
Platform: UNKNOWN
